xtracture/__init__.py
xtracture/extractor.py
xtracture/item_extractor.py
xtracture/logger.py
xtracture/schema.py
xtracture/text_extractor.py
xtracture-0.4.0.dist-info/WHEEL
xtracture-0.4.0.dist-info/METADATA
xtracture-0.4.0.dist-info/RECORD
