Metadata-Version: 2.1
Name: xtracture
Version: 0.4.0
Summary: Xtracture is an open source library designed to efficiently extract arbitrary elements from documents.
Author: ryo.ishii
Author-email: ryoishii1101@gmail.com
Requires-Python: >=3.10,<4.0
Classifier: Programming Language :: Python :: 3
Classifier: Programming Language :: Python :: 3.10
Classifier: Programming Language :: Python :: 3.11
Requires-Dist: google-cloud-vision (>=3.4.0,<4.0.0)
Requires-Dist: langchain (>=0.0.117,<0.0.118)
Requires-Dist: openai (>=0.27.2,<0.28.0)
Requires-Dist: pyocr (>=0.8.3,<0.9.0)
